.bettercodehub.yml
.clang-format
.cmake-format
.gitignore
.markdownlint.yaml
CHANGELOG.md
CMakeLists.txt
CODE_OF_CONDUCT.md
LICENSE.md
README.md
codecov.yml
codespellignore
config.h.cmake
dune.module
ikarus.pc.in
iwyu.imp
pyproject.toml
setup.py
.github/ISSUE_TEMPLATE/bug_report.md
.github/ISSUE_TEMPLATE/feature_request.md
.github/workflows/createDockerContainer.yml
.github/workflows/createRelease.yml
.github/workflows/debian-coverage.yml
.github/workflows/debian.yml
.github/workflows/docsDryRun.yml
.github/workflows/ghpages.yml
.github/workflows/releasePythonPackage.yml
.github/workflows/releasePythonPackageTest.yml
.github/workflows/runExamples.yml
.github/workflows/style.yml
.github/workflows/testpythonpackage.yml
.github/workflows/updatelicense.yml
.github/workflows/scripts/release.py
.github/workflows/scripts/updatelicense.py
.reuse/dep5
LICENSES/CC-BY-SA-4.0.txt
LICENSES/CC0-1.0.txt
LICENSES/LGPL-3.0-or-later.txt
LICENSES/MIT.txt
LICENSES/MPL-2.0.txt
cmake/CMakeLists.txt
cmake/CPM.cmake
cmake/tools.cmake
cmake/FormatTarget/CMakeLists.txt
cmake/modules/AddAutoDiffFlags.cmake
cmake/modules/AddEigenFlags.cmake
cmake/modules/AddMatplotppFlags.cmake
cmake/modules/AddMuesliFlags.cmake
cmake/modules/AddSpdlogFlags.cmake
cmake/modules/AddSpectraFlags.cmake
cmake/modules/CMakeLists.txt
cmake/modules/IkarusMacros.cmake
docs/CMakeLists.txt
docs/literature.bib
docs/mkdocs-macros.py
docs/mkdocs.insiders.yml
docs/mkdocs.yml
docs/__pycache__/mkdocs-macros.cpython-39.pyc
docs/__pycache__/mkdocs-macros.cpython-39.pyc.license
docs/overrides/partials/comments.html
docs/website/.meta.yml
docs/website/about.md
docs/website/download.md
docs/website/gallery.md
docs/website/index.md
docs/website/01_framework/assembler.md
docs/website/01_framework/controlRoutines.md
docs/website/01_framework/differentiablefunction.md
docs/website/01_framework/dirichletBCs.md
docs/website/01_framework/feRequirements.md
docs/website/01_framework/finiteElements.md
docs/website/01_framework/grids.md
python/pyikarus.egg-info/PKG-INFO
python/pyikarus.egg-info/SOURCES.txt
python/pyikarus.egg-info/dependency_links.txt
python/pyikarus.egg-info/requires.txt
python/pyikarus.egg-info/top_level.txt
