Metadata-Version: 2.1
Name: pyikarus
Version: 0.4.7
Home-page: 
Author: ikarus@ibb.uni-stuttgart.de
Author-email: ikarus@ibb.uni-stuttgart.de
Classifier: Programming Language :: C++
Classifier: Programming Language :: Python :: 3
Classifier: License :: OSI Approved :: GNU General Public License (GPL)
Requires-Python: >=3.4
License-File: LICENSE.md
